activetick_http/__init__.py
activetick_http/quote_fields.py
activetick_http-0.12.1.dist-info/DESCRIPTION.rst
activetick_http-0.12.1.dist-info/METADATA
activetick_http-0.12.1.dist-info/RECORD
activetick_http-0.12.1.dist-info/WHEEL
activetick_http-0.12.1.dist-info/metadata.json
activetick_http-0.12.1.dist-info/top_level.txt
