Metadata-Version: 2.0
Name: activetick-http
Version: 0.12.1
Summary: Pandas wrapper for ActiveTick HTTP Proxy
Home-page: https://github.com/uberscientist/activetick_http
Author: Christopher Toledo
Author-email: chris@mindsforge.com
License: MIT
Keywords: activetick,finance,quant,pandas
Platform: UNKNOWN
Classifier: Intended Audience :: Developers
Classifier: License :: OSI Approved :: MIT License
Classifier: Operating System :: OS Independent
Classifier: Programming Language :: Python
Classifier: Programming Language :: Python :: 3
Classifier: Programming Language :: Python :: 3.3
Classifier: Programming Language :: Python :: 3.4
Classifier: Programming Language :: Python :: 3.5
Requires-Dist: numpy
Requires-Dist: pandas
Requires-Dist: redis
Requires-Dist: requests
